attempt/__init__.py
attempt/test_attempt.py
attempt-0.1.1.dist-info/LICENSE
attempt-0.1.1.dist-info/METADATA
attempt-0.1.1.dist-info/WHEEL
attempt-0.1.1.dist-info/RECORD
