Metadata-Version: 2.1
Name: attempt
Version: 0.1.1
Summary: 
Author: J. M. F. Tsang
Author-email: j.m.f.tsang@cantab.net
Requires-Python: >=3.10,<4.0
Classifier: Programming Language :: Python :: 3
Classifier: Programming Language :: Python :: 3.10
Classifier: Programming Language :: Python :: 3.11
Classifier: Programming Language :: Python :: 3.12
